multihypergraph/__init__.py
multihypergraph/hashable_counter.py
multihypergraph/morphisms.py
multihypergraph/objects.py
tests/__init__.py
tests/context.py
tests/test_hashable_counter.py
tests/test_morphisms.py
tests/test_objects.py
multihypergraph-0.0.1.dist-info/LICENSE
multihypergraph-0.0.1.dist-info/METADATA
multihypergraph-0.0.1.dist-info/WHEEL
multihypergraph-0.0.1.dist-info/top_level.txt
multihypergraph-0.0.1.dist-info/RECORD
