Metadata-Version: 2.1
Name: multihypergraph
Version: 0.0.1
Summary: A simple python package for graph theory that supports multi-edges, hyper-edges, looped-edges and every other combination of these.
Home-page: https://github.com/vaibhavkarve/multihypergraph
Author: Vaibhav Karve
Author-email: vaibhavskarve@gmail.com
License: UNKNOWN
Platform: UNKNOWN
Classifier: Programming Language :: Python :: 3
Classifier: License :: OSI Approved :: GNU General Public License v3 (GPLv3)
Classifier: Operating System :: OS Independent
